bci/car_racing/__init__.py
bci/car_racing/car_racing.py
bci/pacman/__init__.py
bci_feedback-0.1.dist-info/LICENSE
bci_feedback-0.1.dist-info/METADATA
bci_feedback-0.1.dist-info/WHEEL
bci_feedback-0.1.dist-info/top_level.txt
bci_feedback-0.1.dist-info/RECORD
